napari_tiff/__init__.py
napari_tiff/_version.py
napari_tiff/napari.yaml
napari_tiff/napari_tiff_colormaps.py
napari_tiff/napari_tiff_metadata.py
napari_tiff/napari_tiff_reader.py
napari_tiff/_tests/__init__.py
napari_tiff/_tests/test_data.py
napari_tiff/_tests/test_tiff_metadata.py
napari_tiff/_tests/test_tiff_reader.py
napari_tiff-0.1.4.dist-info/licenses/LICENSE
napari_tiff-0.1.4.dist-info/METADATA
napari_tiff-0.1.4.dist-info/WHEEL
napari_tiff-0.1.4.dist-info/entry_points.txt
napari_tiff-0.1.4.dist-info/top_level.txt
napari_tiff-0.1.4.dist-info/RECORD
