Metadata-Version: 2.4
Name: napari-tiff
Version: 0.1.4
Summary: official napari tiff reader and writer.
Author: Genevieve Buckley, napari-tiff contributors
Author-email: napari core developers <napari-core-devs@googlegroups.com>
License: 
Project-URL: source, https://github.com/napari/napari-tiff
Project-URL: tracker, https://github.com/napari/napari-tiff/issues
Classifier: Development Status :: 3 - Alpha
Classifier: Intended Audience :: Developers
Classifier: Intended Audience :: Education
Classifier: Intended Audience :: Science/Research
Classifier: Framework :: napari
Classifier: Programming Language :: Python
Classifier: Programming Language :: Python :: 3
Classifier: Programming Language :: Python :: 3.10
Classifier: Programming Language :: Python :: 3.11
Classifier: Programming Language :: Python :: 3.12
Classifier: Topic :: Software Development :: Libraries
Classifier: Topic :: Scientific/Engineering
Classifier: Programming Language :: Python :: Implementation :: CPython
Classifier: Operating System :: OS Independent
Classifier: License :: OSI Approved :: BSD License
Requires-Python: >=3.10
License-File: LICENSE
Requires-Dist: numpy
Requires-Dist: tifffile[codecs,zarr]>=2024.7.21
Provides-Extra: testing
Requires-Dist: build; extra == "testing"
Requires-Dist: pytest; extra == "testing"
Requires-Dist: tox; extra == "testing"
Dynamic: license-file
